CHANGES.rst
CONTRIBUTORS.rst
MANIFEST.in
README.rst
setup.cfg
setup.py
docs/LICENSE.GPL
docs/LICENSE.rst
docs/index.rst
src/collective/__init__.py
src/collective.js.unitegallery.egg-info/PKG-INFO
src/collective.js.unitegallery.egg-info/SOURCES.txt
src/collective.js.unitegallery.egg-info/dependency_links.txt
src/collective.js.unitegallery.egg-info/entry_points.txt
src/collective.js.unitegallery.egg-info/namespace_packages.txt
src/collective.js.unitegallery.egg-info/not-zip-safe
src/collective.js.unitegallery.egg-info/requires.txt
src/collective.js.unitegallery.egg-info/top_level.txt
src/collective/js/__init__.py
src/collective/js/unitegallery/__init__.py
src/collective/js/unitegallery/configure.zcml
src/collective/js/unitegallery/interfaces.py
src/collective/js/unitegallery/setuphandlers.py
src/collective/js/unitegallery/testing.py
src/collective/js/unitegallery/browser/__init__.py
src/collective/js/unitegallery/browser/configure.zcml
src/collective/js/unitegallery/browser/overrides/.gitkeep
src/collective/js/unitegallery/browser/static/.gitkeep
src/collective/js/unitegallery/browser/static/release_log.txt
src/collective/js/unitegallery/browser/static/css/unite-gallery.css
src/collective/js/unitegallery/browser/static/images/button-close.png
src/collective/js/unitegallery/browser/static/images/cover-grid.png
src/collective/js/unitegallery/browser/static/images/icon-link32.png
src/collective/js/unitegallery/browser/static/images/icon-play32.png
src/collective/js/unitegallery/browser/static/images/icon-zoom32.png
src/collective/js/unitegallery/browser/static/images/lightbox-arrow-left.png
src/collective/js/unitegallery/browser/static/images/lightbox-arrow-right.png
src/collective/js/unitegallery/browser/static/images/lightbox-icon-close-compact.png
src/collective/js/unitegallery/browser/static/images/lightbox-icon-close-compact2.png
src/collective/js/unitegallery/browser/static/images/lightbox-icon-close.png
src/collective/js/unitegallery/browser/static/images/loader-black1.gif
src/collective/js/unitegallery/browser/static/images/loader-black2.gif
src/collective/js/unitegallery/browser/static/images/loader-black3.gif
src/collective/js/unitegallery/browser/static/images/loader-black4.gif
src/collective/js/unitegallery/browser/static/images/loader-black5.gif
src/collective/js/unitegallery/browser/static/images/loader-black6.gif
src/collective/js/unitegallery/browser/static/images/loader-black7.gif
