Metadata-Version: 1.1
Name: collective.js.unitegallery
Version: 1.0a1
Summary: Adds unitegallery javascripts to registry
Home-page: https://pypi.python.org/pypi/collective.js.unitegallery
Author: Martronic-SA
Author-email: martronic@martronic.ch
License: GPL version 2
Keywords: Python Plone
Platform: UNKNOWN
Classifier: Environment :: Web Environment
Classifier: Framework :: Plone
Classifier: Framework :: Plone :: 5.0
Classifier: Programming Language :: Python
Classifier: Programming Language :: Python :: 2.7
Classifier: Operating System :: OS Independent
Classifier: License :: OSI Approved :: GNU General Public License v2 (GPLv2)
